catparser/AstPostProcessor.py
catparser/AstValidator.py
catparser/CatsLarkParser.py
catparser/__init__.py
catparser/__main__.py
catparser/ast.py
catparser/grammar/catbuffer.lark
catparser-3.1.0.data/data/grammar/catbuffer.lark
catparser-3.1.0.dist-info/LICENSE
catparser-3.1.0.dist-info/METADATA
catparser-3.1.0.dist-info/WHEEL
catparser-3.1.0.dist-info/top_level.txt
catparser-3.1.0.dist-info/RECORD
