Metadata-Version: 2.1
Name: catparser
Version: 3.1.0
Summary: Symbol Catbuffer Parser
Home-page: https://github.com/symbol/catbuffer-parser
Author: Symbol Contributors
Author-email: contributors@symbol.dev
License: MIT
Keywords: symbol,catbuffer,catparser,parser,catbuffer-parser
Platform: UNKNOWN
Classifier: Programming Language :: Python :: 3.6
Obsoletes: catbuffer_parser
License-File: LICENSE
